flet_fastapi_proxy_path/__init__.py
flet_fastapi_proxy_path/app.py
flet_fastapi_proxy_path/flet_app.py
flet_fastapi_proxy_path/flet_app_manager.py
flet_fastapi_proxy_path/flet_fastapi.py
flet_fastapi_proxy_path/flet_oauth.py
flet_fastapi_proxy_path/flet_static_files.py
flet_fastapi_proxy_path/flet_upload.py
flet_fastapi_proxy_path/oauth_state.py
flet_fastapi_proxy_path/once.py
flet_fastapi_proxy_path/version.py
flet_fastapi_proxy_path-0.1.2.dist-info/METADATA
flet_fastapi_proxy_path-0.1.2.dist-info/WHEEL
flet_fastapi_proxy_path-0.1.2.dist-info/RECORD
